README.rst
setup.py
txrest/__init__.py
txrest/json.py
txrest/mixin.py
txrest/text.py
txrest/xml.py
txrest.egg-info/PKG-INFO
txrest.egg-info/SOURCES.txt
txrest.egg-info/dependency_links.txt
txrest.egg-info/requires.txt
txrest.egg-info/top_level.txt