Metadata-Version: 1.1
Name: txrest
Version: 0.6.3
Summary: Asynchronous Rest/JSON API using Twisted
Home-page: https://github.com/bendemott/txrest.git
Author: Ben DeMott
Author-email: ben.demott@gmail.com
License: MIT
Keywords: twisted,rest,json,resource,api
Platform: UNKNOWN
Classifier: Development Status :: 5 - Production/Stable
Classifier: Intended Audience :: Developers
Classifier: License :: OSI Approved :: MIT License
Classifier: Operating System :: MacOS :: MacOS X
Classifier: Operating System :: Microsoft :: Windows
Classifier: Operating System :: POSIX
Classifier: Programming Language :: Python
Classifier: Programming Language :: Python :: 2
Classifier: Programming Language :: Python :: 2.6
Classifier: Programming Language :: Python :: 2.7
Classifier: Topic :: Software Development :: Libraries :: Python Modules
Classifier: Topic :: Internet :: WWW/HTTP :: HTTP Servers
